plone.formwidget.autocomplete-1.5.0-py3.13-nspkg.pth
plone/formwidget/autocomplete/README.txt
plone/formwidget/autocomplete/__init__.py
plone/formwidget/autocomplete/configure.zcml
plone/formwidget/autocomplete/demo.py
plone/formwidget/autocomplete/demo.zcml
plone/formwidget/autocomplete/display.pt
plone/formwidget/autocomplete/input.pt
plone/formwidget/autocomplete/interfaces.py
plone/formwidget/autocomplete/testing.zcml
plone/formwidget/autocomplete/tests.py
plone/formwidget/autocomplete/widget.py
plone/formwidget/autocomplete/jquery-autocomplete/formwidget-autocomplete.js
plone/formwidget/autocomplete/jquery-autocomplete/indicator.gif
plone/formwidget/autocomplete/jquery-autocomplete/jquery.autocomplete.css
plone/formwidget/autocomplete/jquery-autocomplete/jquery.autocomplete.js
plone/formwidget/autocomplete/jquery-autocomplete/jquery.autocomplete.min.js
plone/formwidget/autocomplete/jquery-autocomplete/jquery.autocomplete.pack.js
plone/formwidget/autocomplete/jquery-autocomplete/jquery.bgiframe.min.js
plone/formwidget/autocomplete/profiles/plone4/cssregistry.xml
plone/formwidget/autocomplete/profiles/plone4/jsregistry.xml
plone/formwidget/autocomplete/profiles/plone4/metadata.xml
plone/formwidget/autocomplete/profiles/plone5/metadata.xml
plone/formwidget/autocomplete/profiles/plone5/registry.xml
plone/formwidget/autocomplete/profiles/plone6/metadata.xml
plone/formwidget/autocomplete/profiles/plone6/registry.xml
plone/formwidget/autocomplete/profiles/uninstall/cssregistry.xml
plone/formwidget/autocomplete/profiles/uninstall/jsregistry.xml
plone/formwidget/autocomplete/profiles/uninstall/registry.xml
plone/formwidget/autocomplete/upgrades/__init__.py
plone/formwidget/autocomplete/upgrades/configure.zcml
plone/formwidget/autocomplete/upgrades/to1.py
plone_formwidget_autocomplete-1.5.0.dist-info/METADATA
plone_formwidget_autocomplete-1.5.0.dist-info/WHEEL
plone_formwidget_autocomplete-1.5.0.dist-info/entry_points.txt
plone_formwidget_autocomplete-1.5.0.dist-info/namespace_packages.txt
plone_formwidget_autocomplete-1.5.0.dist-info/top_level.txt
plone_formwidget_autocomplete-1.5.0.dist-info/RECORD
